knit_langgraph/__init__.py
knit_langgraph/client/__init__.py
knit_langgraph/client/auth_client.py
knit_langgraph/client/http_client.py
knit_langgraph/client/sdk_client.py
knit_langgraph/exceptions/exceptions.py
knit_langgraph/logger.py
knit_langgraph/models/tools_filter.py
knit_langgraph/models/tools_summary.py
knit_langgraph/utils/constants.py
knit_langgraph/utils/json_schema_to_pydantic.py
knit_langgraph-0.1.2.dist-info/METADATA
knit_langgraph-0.1.2.dist-info/WHEEL
knit_langgraph-0.1.2.dist-info/RECORD
