Metadata-Version: 2.3
Name: knit-langgraph
Version: 0.1.2
Summary: The Knit LangGraph SDK enables seamless integration between LangGraph-powered agents and SaaS applications. This toolkit allows developers to easily connect AI agents with hundreds of SaaS platforms using Knit's integration platform. With minimal code, expand your AI assistant's capabilities by incorporating external data and functionalities from popular business applications.
Author: Akshat - Knit
Author-email: akshat@getknit.dev
Requires-Python: >=3.9,<4.0
Classifier: Programming Language :: Python :: 3
Classifier: Programming Language :: Python :: 3.9
Classifier: Programming Language :: Python :: 3.10
Classifier: Programming Language :: Python :: 3.11
Classifier: Programming Language :: Python :: 3.12
Classifier: Programming Language :: Python :: 3.13
Requires-Dist: httpx (>=0.28.1)
Requires-Dist: langchain-core (>=0.2)
Requires-Dist: langgraph (>=0.2)
